mcp_seniverse_weather_zy/__init__.py
mcp_seniverse_weather_zy/__main__.py
mcp_seniverse_weather_zy/server.py
mcp_seniverse_weather_zy-1.0.0.dist-info/METADATA
mcp_seniverse_weather_zy-1.0.0.dist-info/WHEEL
mcp_seniverse_weather_zy-1.0.0.dist-info/entry_points.txt
mcp_seniverse_weather_zy-1.0.0.dist-info/RECORD
